simple_dotdict/__init__.py
simple_dotdict-1.0.0.dist-info/LICENSE
simple_dotdict-1.0.0.dist-info/METADATA
simple_dotdict-1.0.0.dist-info/WHEEL
simple_dotdict-1.0.0.dist-info/RECORD
