Metadata-Version: 2.1
Name: simple-dotdict
Version: 1.0.0
Summary: Dot.notation access for dictionaries
Author: Jacob Valdez
Author-email: jacobfv123@gmail.com
Requires-Python: >=3.8,<4.0
Classifier: Programming Language :: Python :: 3
Classifier: Programming Language :: Python :: 3.8
Classifier: Programming Language :: Python :: 3.9
Classifier: Programming Language :: Python :: 3.10
Classifier: Programming Language :: Python :: 3.11
